drifto
